digital_building_blocks_lib/combinational.v
`timescale 1ns / 1ps
//////////////////////////////////////////////////////////////////////////////////
// Company: 
// Engineer: 
// 
// Create Date: 09/30/2021 08:30:32 PM
// Design Name: 
// Module Name: sequential
// Project Name: 
// Target Devices: 
// Tool Versions: 
// Description: 
// 
// Dependencies: 
// 
// Revision:
// Revision 0.01 - File Created
// Additional Comments:
// 
//////////////////////////////////////////////////////////////////////////////////

/*
module combinational(

    );
endmodule
*/

module  Dec(a, b) ;
    parameter n = 2 ;
    parameter m = 4 ;
    
    input [n-1:0] a ;
    output [m-1:0] b ; 
    
    wire [m-1:0] b = 1<<a ;
endmodule

module Mux3(a2, a1, a0, s, b) ;
    parameter k = 1 ;
    input[k-1:0] a0, a1, a2 ; // inputs
    input[2:0] s ; // one hot select
    output[k-1:0] b;
    
    wire [k-1:0] b =  ({k{s[0]}} & a0) |
                      ({k{s[1]}} & a1) |
                      ({k{s[2]}} & a2) ; 
endmodule

module Muxb3(a2, a1, a0, sb, b) ;
    parameter k = 1 ;
    input[k-1:0] a0, a1, a2 ; // inputs
    input[1:0] sb ; // binary select
    output[k-1:0] b;
    wire [3:0] s ;
    
    Dec #(2, 3) d(sb, s) ;
    Mux3 #(k) m(a2, a1, a0, s, b) ;
endmodule

module Mux6a(a5, a4, a3, a2, a1, a0, s, b) ;
    parameter k = 1 ;
    input [k-1:0] a0, a1, a2, a3, a4, a5  ; // inputs
    input [5:0] s ; // one hot select
    output [k-1:0] b;
    wire [k-1:0] ba, bb ;
    wire [k-1:0] b = ba | bb ;
    
    Mux3 #(k) ma(a2, a1, a0, s[2:0], ba) ;
    Mux3 #(k) mb(a5, a4, a3, s[5:3], bb) ;
endmodule
/*
module Enc42(a, b) ;
    input [3:0] a ;    
    output [1:0] b ;
    wire [1:0] b = {a[3] | a[2], a[3] | a[1]} ;
endmodule

module Enc42a(a, b, c) ;
    input [3:0] a ;
    output [1:0] b ;
    output c ;
    wire [1:0] b = {a[3] | a[2], a[3] | a[1]} ;
    wire c = |a ;
endmodule

module Enc164(a, b) ;
    input [15:0] a ;
    output [3:0] b ;
    wire [3:0] b ;
    wire [7:0] c ; 
    wire [3:0] d ; 
    
    Enc42a e0(a[3:0], c[1:0], d[0]) ;
    Enc42a e1(a[7:4], c[3:2], d[1]) ;
    Enc42a e2(a[11:8], c[5:4], d[2]) ;
    Enc42a e3(a[15:12], c[7:6], d[3]) ;
    
    Enc42 e4(d[3:0], b[3:2]) ;
    
    assign b[1] = c[1] | c[3] | c[5] | c[7] ;
    assign b[0] = c[0] | c[2] | c[4] | c[6] ;
    
endmodule

module Arb(r, g) ; 
    parameter n = 8 ;
    input [n-1:0] r ;
    output [n-1:0] g ;
    wire [n-1:0] c = {(~r[n-2:0] & c[n-2:0]), 1'b1} ;
    wire [n-1:0] g = r & c ; 
endmodule

module RArb(r, g) ;
    parameter n = 8 ;
    input [n-1:0] r ;
    output [n-1:0] g ;
    wire [n-1:0] c = {1'b1, (~r[n-1:1] & c[n-1:1])} ;
    wire [n-1:0] g = r & c ;
endmodule

module PriorityEncoder83(r, b) ; 
    input [7:0] r ;
    output [2:0] b ;
    wire [7:0] g ;
    Arb #(8) a(r, g) ; 
    Enc83 e(g, b) ;
endmodule

module EqComp(a, b, eq) ;
    parameter k = 8 ;
    input [k-1:0] a, b ;
    output eq ;
    wire eq = (a == b) ;
endmodule

module MagComp(a, b, gt) ;
    parameter k = 8 ;
    input [k-1:0] a, b; 
    output gt ;
    wire [k-1:0] eqi = a ~^ b ;
    wire [k-1:0] gti = a & ~b ; 
    wire [k:0] gtb = {((eqi[k-1:0] & gtb[k-1:0]) | gti[k-1:0]), 1'b0} ;
    wire gt = gtb[k] ;
endmodule

module counter(clk, reset, enable, count);
    input clk, reset, enable;
    output count;
    parameter counterSize = 8;
    
    wire clk;
    wire reset;
    wire enable;
    
    reg[counterSize:0] counterOut;
    
    always @(posedge clk)
    begin:
        if (reset == 1'b1) begin
            counterOut <= {counterSize{1'b0}}
        end
        else if (enable == 1'b1) begin
            counterOut <= counterOut + 1;
        end
    end
endmodule
*/

digital_building_blocks_lib/combinational_tb.v
module combinational_tb;

/*
parameter n = 2;
parameter m = 4;
reg [n-1:0] a;
wire [m-1:0] b;

Dec #(n,m) d1(a,b);



parameter k = 4;
reg [k-1 : 0] a0, a1, a2;
reg [2:0] s;
wire [3:0] b;

Mux3 #(k) mux(a2, a1, a0, s, b);


parameter k = 4;
reg [k-1 : 0] a0, a1, a2;
reg [1:0] sb;
wire [k-1:0] b;

Muxb3 #(k) muxb(a2, a1, a0, sb, b);
*/

parameter k = 4;
reg [k-1 : 0] a0, a1, a2, a3, a4, a5;
reg [5:0] s;
wire [k-1:0] b;

Mux6a #(k) mux6(a0, a1, a2, a3, a4, a5, s, b);




// Test each possible input of a for decoder
/*
initial begin
    $monitor("At time %t, a = %d, b = %d", $time, a, b);
    $dumpfile("combinational_tb.vcd");
    $dumpvars(0, combinational_tb);
    # 5 a = 0;
    # 5 a = 1;
    # 5 a = 2;
    # 5 a = 3;
end

// Test for mux3
initial begin
    $monitor("At time %t, a0 = %d, a1 = %d, a2 = %d, sb = %d, b = %d", $time, a0, a1, a2, sb, b);
    $dumpfile("combinational_tb.vcd");
    $dumpvars(0, combinational_tb);
    
    # 5
    a0 = 0;
    a1 = 0;
    a2 = 0;
    s = 0;
    
    # 5
    a0 = 1;
    a1 = 2;
    a2 = 4;
    s = 0;
    
    # 5
    s = 1;
    
    #5
    s = 2;
    
    #5
    s = 4;
    
    #5
    $finish;
    
end

// muxb3 test 
initial begin
    $monitor("At time %t, a0 = %d, a1 = %d, a2 = %d, sb = %d, b = %d", $time, a0, a1, a2, sb, b);
    $dumpfile("combinational_tb.vcd");
    $dumpvars(0, combinational_tb);
    
    # 5
    a0 = 0;
    a1 = 0;
    a2 = 0;
    sb = 0;
    
    # 5
    a0 = 1;
    a1 = 2;
    a2 = 4;
    sb = 0;
    
    # 5
    sb = 1;
    
    #5
    sb = 2;
    
    #5
    sb = 4;
    
    #5
    $finish;
    
end

*/

// mux6 test
initial begin
    $monitor("At time %t, a0 = %d, a1 = %d, a2 = %d, a3 = %d, a4 = %d, a5 = %d, s = %d, b = %d", $time, a0, a1, a2, a3, a4, a5, s, b);
    $dumpfile("combinational_tb.vcd");
    $dumpvars(0, combinational_tb);
    
    # 5
    a0 = 1;
    a1 = 2;
    a2 = 3;
    a3 = 4;
    a4 = 5;
    a5 = 6;
    
    # 5
    
    s = 6'b000001;
    
    # 5

    s = 6'b000010;
    
    # 5
    s = 6'b000100;
    
    #5
    s = 6'b001000;
    
    #5
    s = 6'b010000;
    
    #5
    s = 6'b100000;
    #5
    
    $finish;
    
end



endmodule

digital_building_blocks_lib/combinational_tb.vcd
$date
	Fri Apr 28 13:07:05 2023
$end
$version
	Icarus Verilog
$end
$timescale
	1ps
$end
$scope module combinational_tb $end
$var wire 4 ! b [3:0] $end
$var reg 4 " a0 [3:0] $end
$var reg 4 # a1 [3:0] $end
$var reg 4 $ a2 [3:0] $end
$var reg 4 % a3 [3:0] $end
$var reg 4 & a4 [3:0] $end
$var reg 4 ' a5 [3:0] $end
$var reg 6 ( s [5:0] $end
$scope module mux6 $end
$var wire 4 ) a0 [3:0] $end
$var wire 4 * a1 [3:0] $end
$var wire 4 + a2 [3:0] $end
$var wire 4 , a3 [3:0] $end
$var wire 4 - a4 [3:0] $end
$var wire 4 . a5 [3:0] $end
$var wire 4 / b [3:0] $end
$var wire 6 0 s [5:0] $end
$var wire 4 1 bb [3:0] $end
$var wire 4 2 ba [3:0] $end
$scope module ma $end
$var wire 4 3 a0 [3:0] $end
$var wire 4 4 a1 [3:0] $end
$var wire 4 5 a2 [3:0] $end
$var wire 4 6 b [3:0] $end
$var wire 3 7 s [2:0] $end
$upscope $end
$scope module mb $end
$var wire 4 8 a0 [3:0] $end
$var wire 4 9 a1 [3:0] $end
$var wire 4 : a2 [3:0] $end
$var wire 4 ; b [3:0] $end
$var wire 3 < s [2:0] $end
$upscope $end
$upscope $end
$upscope $end
$enddefinitions $end
#0
$dumpvars
bx <
bx ;
bx :
bx 9
bx 8
bx 7
bx 6
bx 5
bx 4
bx 3
bx 2
bx 1
bx 0
bx /
bx .
bx -
bx ,
bx +
bx *
bx )
bx (
bx '
bx &
bx %
bx $
bx #
bx "
bx !
$end
#5000
b0xxx !
b0xxx /
b0xxx 2
b0xxx 6
b0xx 1
b0xx ;
b110 '
b110 )
b110 3
b101 &
b101 *
b101 4
b100 %
b100 +
b100 5
b11 $
b11 ,
b11 8
b10 #
b10 -
b10 9
b1 "
b1 .
b1 :
#10000
b110 !
b110 /
b110 2
b110 6
b0 1
b0 ;
b1 7
b0 <
b1 (
b1 0
#15000
b101 !
b101 /
b101 2
b101 6
b10 7
b10 (
b10 0
#20000
b100 !
b100 /
b100 2
b100 6
b100 7
b100 (
b100 0
#25000
b11 !
b11 /
b11 1
b11 ;
b0 2
b0 6
b0 7
b1 <
b1000 (
b1000 0
#30000
b10 !
b10 /
b10 1
b10 ;
b10 <
b10000 (
b10000 0
#35000
b1 !
b1 /
b1 1
b1 ;
b100 <
b100000 (
b100000 0
